{
  "todos": [
    {
      "id": 1678971010709,
      "title": "Format the data of firebase"
    },
    {
      "id": 1678972845427,
      "title": "Format the data of firebase"
    },
    {
      "id": 1678986463694,
      "title": "Format the data of firebase"
    },
    {
      "id": 1678987870604,
      "title": "Format the data of firebase"
    },
    {
      "id": 1678987967011,
      "title": "Format the data of firebase"
    },
    {
      "id": 1678988555748,
      "title": "Format the data of firebase"
    }
  ]
}